pyRetroGame/__init__.py
pyRetroGame/assets.py
pyRetroGame/game.py
pyRetroGame/gameMath.py
pyRetroGame/objects.py
pyRetroGame/osApi.py
pyRetroGame/vector.py
pyRetroGame-1.1.29.dist-info/METADATA
pyRetroGame-1.1.29.dist-info/WHEEL
pyRetroGame-1.1.29.dist-info/top_level.txt
pyRetroGame-1.1.29.dist-info/RECORD
